mcrender/__init__.py
mcrender/_cli.py
mcrender/_util.py
mcrender/_data/default-config.conf
mcrender/_data/blender/mineways-isometric.blend
mcrender/_data/blender/mineways-isometric.py.txt
mcrender-2.0.0.dist-info/COPYING.txt
mcrender-2.0.0.dist-info/METADATA
mcrender-2.0.0.dist-info/WHEEL
mcrender-2.0.0.dist-info/entry_points.txt
mcrender-2.0.0.dist-info/top_level.txt
mcrender-2.0.0.dist-info/RECORD
