Metadata-Version: 2.1
Name: mcrender
Version: 2.0.0
Summary: Command-line tool and Python library for creating isometric Minecraft renders with Mineways and Blender.
Home-page: https://github.com/avdstaaij/mcrender
Author: Arthur van der Staaij
Author-email: arthurvanderstaaij@gmail.com
License: GPL-3.0-or-later
Project-URL: Bug Reports, https://github.com/avdstaaij/mcrender/issues
Project-URL: Source, https://github.com/avdstaaij/mcrender
Keywords: Minecraft,Mineways,Blender,rendering,isometric,3D,3D modeling,3D rendering,cli,automation
Classifier: Development Status :: 5 - Production/Stable
Classifier: Environment :: Console
Classifier: Intended Audience :: End Users/Desktop
Classifier: Intended Audience :: Developers
Classifier: Intended Audience :: Science/Research
Classifier: License :: OSI Approved :: GNU General Public License v3 or later (GPLv3+)
Classifier: Natural Language :: English
Classifier: Programming Language :: Python :: 3
Classifier: Topic :: Artistic Software
Classifier: Topic :: Games/Entertainment :: Simulation
Classifier: Topic :: Multimedia :: Graphics :: 3D Modeling
Classifier: Topic :: Multimedia :: Graphics :: 3D Rendering
Classifier: Topic :: Scientific/Engineering :: Visualization
Classifier: Topic :: Software Development :: Libraries :: Python Modules
Classifier: Topic :: Software Development :: Version Control :: Git
Requires-Python: >=3.7, <4
License-File: COPYING.txt
Requires-Dist: cloup>=3.0.0
Requires-Dist: Pillow
Requires-Dist: platformdirs>=3.2.0
